responsiveimage/__init__.py
responsiveimage/__main__.py
responsiveimage/argsResponsiveImage.py
responsiveimage/copy_image.py
responsiveimage/exif.py
responsiveimage/jpg.py
responsiveimage/misc.py
responsiveimage/mp4.py
responsiveimage/pil_image.py
responsiveimage/png.py
responsiveimage/webp.py
responsiveimage-1.7.0.dist-info/licenses/LICENSE
responsiveimage-1.7.0.dist-info/METADATA
responsiveimage-1.7.0.dist-info/WHEEL
responsiveimage-1.7.0.dist-info/top_level.txt
responsiveimage-1.7.0.dist-info/RECORD
