Metadata-Version: 2.4
Name: responsiveimage
Version: 1.7.0
Summary: Create different scaled versions of an image, in webp, jpg, png, svg,... to be used on responsive website
Author-email: Pascal Brand <pascal.brand38@gmail.com>
License: UNKNOWN
Project-URL: Homepage, https://github.com/pascal-brand38/py-responsiveimage
Project-URL: Bug Tracker, https://github.com/pascal-brand38/py-responsiveimage/issues
Platform: UNKNOWN
Classifier: Programming Language :: Python :: 3
Classifier: Operating System :: OS Independent
Requires-Python: >=3.8
License-File: LICENSE
Requires-Dist: Pillow
Requires-Dist: filetype
Dynamic: license-file
